setup.py
bda/__init__.py
bda.daemon.egg-info/PKG-INFO
bda.daemon.egg-info/SOURCES.txt
bda.daemon.egg-info/dependency_links.txt
bda.daemon.egg-info/namespace_packages.txt
bda.daemon.egg-info/top_level.txt
bda.daemon.egg-info/zip-safe
bda/daemon/__init__.py
bda/daemon/daemon.py
tests/__init__.py
tests/scaffold.py
tests/test_daemon.py