Metadata-Version: 1.0
Name: bda.daemon
Version: 1.1.1
Summary: takes a class and runs it as a simple daemon.
Home-page: http://svn.plone.org/svn/collective/bda.daemon
Author: Robert Niederreiter
Author-email: rnix@squarewave.at
License: GPL
Keywords: daemon fork
Platform: UNKNOWN
